
{
  "title": {
    "text": "big complexity | g++-5 "
  },
  "xAxis": {
    "title": {
      "text": "Number of bindings"
    },
    "floor": 0
  },

  "yAxis": {
    "title": {
      "text": "Time [s]"
    },
    "floor": 0
  },
  "series": [
    {
      "name": "ctor/auto",
      "data": [[0, 9.48525], [20, 9.40461], [40, 9.62371], [60, 10.0177], [80, 10.3394], [100, 10.5769], [120, 10.9483], [140, 11.3865], [160, 11.7919], [180, 12.3521], [200, 13.0116]]
    },
    {
      "name": "inject/all",
      "data": [[0, 7.85724], [20, 8.0421], [40, 8.30985], [60, 8.27425], [80, 9.36074], [100, 12.6836], [120, 10.4856], [140, 9.23772], [160, 12.797], [180, 12.0132], [200, 10.4686]]
    },
    {
      "name": "ctor/exposed",
      "data": [[0, 9.57794], [20, 10.1463], [40, 10.8936], [60, 12.001], [80, 19.5554], [100, 18.6045], [120, 16.899], [140, 22.8715], [160, 33.4548], [180, 26.8824], [200, 25.3676]]
    },
    {
      "name": "inject/exposed",
      "data": [[0, 8.05855], [20, 8.50122], [40, 9.48915], [60, 9.3967], [80, 15.2308], [100, 10.5326], [120, 11.7288], [140, 14.5994], [160, 13.8765], [180, 15.1027], [200, 20.8738]]
    }
  ]
}
