
{
  "title": {
    "text": "big complexity | g++-6 "
  },
  "xAxis": {
    "title": {
      "text": "Number of bindings"
    },
    "floor": 0
  },

  "yAxis": {
    "title": {
      "text": "Time [s]"
    },
    "floor": 0
  },
  "series": [
    {
      "name": "ctor/auto",
      "data": [[0, 12.3993], [20, 12.9335], [40, 12.3907], [60, 12.6881], [80, 13.0326], [100, 13.3494], [120, 13.8658], [140, 13.9609], [160, 14.8919], [180, 15.4788], [200, 15.4002]]
    },
    {
      "name": "inject/all",
      "data": [[0, 10.6348], [20, 10.3486], [40, 10.3326], [60, 10.6447], [80, 11.6591], [100, 11.6318], [120, 13.5661], [140, 12.2893], [160, 12.8061], [180, 13.3104], [200, 13.1582]]
    },
    {
      "name": "ctor/exposed",
      "data": [[0, 12.7141], [20, 13.3148], [40, 13.2769], [60, 15.0001], [80, 16.8144], [100, 18.8037], [120, 20.9241], [140, 23.094], [160, 24.9393], [180, 29.153], [200, 30.897]]
    },
    {
      "name": "inject/exposed",
      "data": [[0, 11.6221], [20, 11.7088], [40, 11.7123], [60, 13.1297], [80, 13.2277], [100, 13.0136], [120, 14.2692], [140, 16.0224], [160, 16.7861], [180, 18.6125], [200, 19.5845]]
    }
  ]
}
