
{
  "title": {
    "text": "big complexity | clang++ "
  },
  "xAxis": {
    "title": {
      "text": "Number of bindings"
    },
    "floor": 0
  },

  "yAxis": {
    "title": {
      "text": "Time [s]"
    },
    "floor": 0
  },
  "series": [
    {
      "name": "ctor/auto",
      "data": [[0, 4.71779], [20, 4.47973], [40, 4.61186], [60, 4.80084], [80, 4.90674], [100, 5.14384], [120, 5.46013], [140, 5.47882], [160, 5.51022], [180, 5.67596], [200, 6.01703]]
    },
    {
      "name": "inject/all",
      "data": [[0, 3.32442], [20, 3.67682], [40, 3.57846], [60, 3.71603], [80, 3.83279], [100, 4.02674], [120, 4.19905], [140, 4.51048], [160, 4.59856], [180, 4.64978], [200, 4.9717]]
    },
    {
      "name": "ctor/exposed",
      "data": [[0, 4.21741], [20, 4.79856], [40, 5.42366], [60, 6.52177], [80, 7.77341], [100, 8.18128], [120, 8.64561], [140, 9.61563], [160, 10.8765], [180, 12.2514], [200, 12.1767]]
    },
    {
      "name": "inject/exposed",
      "data": [[0, 3.54999], [20, 3.57609], [40, 3.76697], [60, 4.23456], [80, 4.44275], [100, 4.89733], [120, 5.47148], [140, 5.92739], [160, 6.9614], [180, 6.86791], [200, 7.1584]]
    }
  ]
}
