
{
  "title": {
    "text": "big complexity | clang++ "
  },
  "xAxis": {
    "title": {
      "text": "Number of bindings"
    },
    "floor": 0
  },

  "yAxis": {
    "title": {
      "text": "Time [s]"
    },
    "floor": 0
  },
  "series": [
    {
      "name": "ctor/auto",
      "data": [[0, 5.18102], [20, 5.26865], [40, 6.27638], [60, 6.46212], [80, 6.27254], [100, 6.71152], [120, 7.59332], [140, 7.03886], [160, 7.29803], [180, 6.38177], [200, 6.86833]]
    },
    {
      "name": "inject/all",
      "data": [[0, 4.77168], [20, 4.4668], [40, 4.61995], [60, 4.15204], [80, 4.32419], [100, 4.97427], [120, 5.10195], [140, 5.07493], [160, 4.86093], [180, 5.43084], [200, 5.60124]]
    },
    {
      "name": "ctor/exposed",
      "data": [[0, 5.36464], [20, 5.26775], [40, 5.71111], [60, 6.49853], [80, 7.22255], [100, 9.70957], [120, 9.62132], [140, 11.0725], [160, 12.7055], [180, 14.1823], [200, 14.656]]
    },
    {
      "name": "inject/exposed",
      "data": [[0, 4.15891], [20, 4.82502], [40, 5.33976], [60, 5.55405], [80, 5.70955], [100, 5.50642], [120, 7.41104], [140, 6.89092], [160, 7.88113], [180, 8.08789], [200, 8.69599]]
    }
  ]
}
