
{
  "title": {
    "text": "big complexity | g++-5 "
  },
  "xAxis": {
    "title": {
      "text": "Number of bindings"
    },
    "floor": 0
  },

  "yAxis": {
    "title": {
      "text": "Time [s]"
    },
    "floor": 0
  },
  "series": [
    {
      "name": "ctor/auto",
      "data": [[0, 10.8904], [20, 10.3499], [40, 10.6173], [60, 10.7727], [80, 11.1243], [100, 11.7237], [120, 12.1772], [140, 12.5361], [160, 13.073], [180, 13.7339], [200, 15.6825]]
    },
    {
      "name": "inject/all",
      "data": [[0, 8.82059], [20, 10.0854], [40, 10.1874], [60, 10.3005], [80, 13.1678], [100, 9.95454], [120, 11.0211], [140, 10.4085], [160, 11.0247], [180, 11.3068], [200, 11.7904]]
    },
    {
      "name": "ctor/exposed",
      "data": [[0, 10.7935], [20, 11.1643], [40, 12.1599], [60, 13.4054], [80, 14.2307], [100, 16.2156], [120, 18.4856], [140, 20.4922], [160, 23.2166], [180, 26.3131], [200, 26.5219]]
    },
    {
      "name": "inject/exposed",
      "data": [[0, 8.44002], [20, 8.77748], [40, 9.55815], [60, 10.3113], [80, 10.7188], [100, 11.5783], [120, 12.7715], [140, 14.1882], [160, 15.2551], [180, 16.6259], [200, 17.3992]]
    }
  ]
}
