
{
  "title": {
    "text": "big complexity | clang++ "
  },
  "xAxis": {
    "title": {
      "text": "Number of bindings"
    },
    "floor": 0
  },

  "yAxis": {
    "title": {
      "text": "Time [s]"
    },
    "floor": 0
  },
  "series": [
    {
      "name": "ctor/auto",
      "data": [[0, 4.69245], [20, 4.17314], [40, 4.55533], [60, 4.71127], [80, 4.76357], [100, 5.13357], [120, 5.70253], [140, 5.78872], [160, 5.98173], [180, 5.62899], [200, 6.31365]]
    },
    {
      "name": "inject/all",
      "data": [[0, 3.85718], [20, 3.55271], [40, 3.60109], [60, 3.92388], [80, 3.89581], [100, 4.28454], [120, 4.39548], [140, 4.71277], [160, 4.7339], [180, 4.51034], [200, 5.63539]]
    },
    {
      "name": "ctor/exposed",
      "data": [[0, 4.57677], [20, 5.04822], [40, 5.72984], [60, 5.95071], [80, 7.18768], [100, 9.57804], [120, 11.2806], [140, 12.8745], [160, 16.358], [180, 21.8321], [200, 19.0233]]
    },
    {
      "name": "inject/exposed",
      "data": [[0, 3.8129], [20, 4.53809], [40, 4.51439], [60, 5.12993], [80, 4.91682], [100, 6.12306], [120, 6.4076], [140, 6.91346], [160, 8.56768], [180, 8.86762], [200, 9.05579]]
    }
  ]
}
