
{
  "title": {
    "text": "big complexity | clang++ "
  },
  "xAxis": {
    "title": {
      "text": "Number of bindings"
    },
    "floor": 0
  },

  "yAxis": {
    "title": {
      "text": "Time [s]"
    },
    "floor": 0
  },
  "series": [
    {
      "name": "ctor/auto",
      "data": [[0, 4.44126], [20, 4.37727], [40, 4.34691], [60, 4.27573], [80, 4.69432], [100, 4.55705], [120, 4.85954], [140, 5.15073], [160, 5.18423], [180, 5.30611], [200, 5.73289]]
    },
    {
      "name": "inject/all",
      "data": [[0, 3.1716], [20, 3.4043], [40, 3.52278], [60, 3.51351], [80, 3.62864], [100, 3.91415], [120, 4.08731], [140, 3.97887], [160, 4.14291], [180, 4.24055], [200, 4.38489]]
    },
    {
      "name": "ctor/exposed",
      "data": [[0, 3.9579], [20, 4.17305], [40, 4.46987], [60, 5.68475], [80, 7.30632], [100, 6.7354], [120, 8.28149], [140, 9.03032], [160, 10.2123], [180, 11.1569], [200, 12.2047]]
    },
    {
      "name": "inject/exposed",
      "data": [[0, 3.58893], [20, 3.63565], [40, 3.90332], [60, 4.18343], [80, 4.4268], [100, 5.2575], [120, 5.62233], [140, 5.905], [160, 6.27915], [180, 6.95374], [200, 7.10489]]
    }
  ]
}
