
{
  "title": {
    "text": "big complexity | clang++ "
  },
  "xAxis": {
    "title": {
      "text": "Number of bindings"
    },
    "floor": 0
  },

  "yAxis": {
    "title": {
      "text": "Time [s]"
    },
    "floor": 0
  },
  "series": [
    {
      "name": "ctor/auto",
      "data": [[0, 5.2272], [20, 5.17225], [40, 5.34622], [60, 5.58846], [80, 5.45634], [100, 5.71507], [120, 5.68847], [140, 5.87675], [160, 5.94187], [180, 6.04366], [200, 6.18317]]
    },
    {
      "name": "inject/all",
      "data": [[0, 2.95178], [20, 3.16478], [40, 3.17983], [60, 3.29415], [80, 3.4024], [100, 3.55739], [120, 3.62746], [140, 3.69619], [160, 3.8271], [180, 3.96183], [200, 4.08738]]
    },
    {
      "name": "ctor/exposed",
      "data": [[0, 5.24882], [20, 5.92705], [40, 6.28524], [60, 6.43838], [80, 7.61162], [100, 8.99027], [120, 9.77296], [140, 10.9401], [160, 12.3664], [180, 14.0026], [200, 14.844]]
    },
    {
      "name": "inject/exposed",
      "data": [[0, 3.3534], [20, 3.45707], [40, 3.46381], [60, 3.75533], [80, 4.04769], [100, 4.37434], [120, 4.89721], [140, 5.50878], [160, 5.71725], [180, 6.17877], [200, 6.41174]]
    }
  ]
}
