
{
  "title": {
    "text": "big complexity | clang++ "
  },
  "xAxis": {
    "title": {
      "text": "Number of bindings"
    },
    "floor": 0
  },

  "yAxis": {
    "title": {
      "text": "Time [s]"
    },
    "floor": 0
  },
  "series": [
    {
      "name": "ctor/auto",
      "data": [[0, 5.12632], [20, 6.46705], [40, 7.98132], [60, 7.46177], [80, 9.31999], [100, 7.53589], [120, 9.84847], [140, 11.0105], [160, 9.33803], [180, 8.78504], [200, 6.14026]]
    },
    {
      "name": "inject/all",
      "data": [[0, 3.52209], [20, 3.25585], [40, 3.93261], [60, 4.37541], [80, 3.95308], [100, 4.9798], [120, 3.92496], [140, 4.13319], [160, 4.91665], [180, 5.16087], [200, 6.14094]]
    },
    {
      "name": "ctor/exposed",
      "data": [[0, 5.02926], [20, 5.08098], [40, 7.02373], [60, 7.36632], [80, 8.84169], [100, 7.95181], [120, 8.68541], [140, 10.3646], [160, 11.3303], [180, 12.9171], [200, 12.9696]]
    },
    {
      "name": "inject/exposed",
      "data": [[0, 3.30449], [20, 3.57827], [40, 3.74988], [60, 4.25637], [80, 4.39269], [100, 5.21684], [120, 5.61726], [140, 5.65956], [160, 6.15324], [180, 7.01022], [200, 8.28723]]
    }
  ]
}
