
{
  "title": {
    "text": "big complexity | clang++ "
  },
  "xAxis": {
    "title": {
      "text": "Number of bindings"
    },
    "floor": 0
  },

  "yAxis": {
    "title": {
      "text": "Time [s]"
    },
    "floor": 0
  },
  "series": [
    {
      "name": "ctor/auto",
      "data": [[0, 5.57402], [20, 5.64481], [40, 5.99072], [60, 6.07508], [80, 5.82228], [100, 6.56791], [120, 6.45908], [140, 6.62729], [160, 7.57812], [180, 6.81908], [200, 7.12937]]
    },
    {
      "name": "inject/all",
      "data": [[0, 3.68707], [20, 3.39933], [40, 3.62091], [60, 3.78047], [80, 5.05456], [100, 4.33644], [120, 4.21001], [140, 4.37164], [160, 4.34621], [180, 4.41053], [200, 4.52776]]
    },
    {
      "name": "ctor/exposed",
      "data": [[0, 5.4609], [20, 5.84956], [40, 6.72261], [60, 6.6248], [80, 8.22249], [100, 9.44559], [120, 10.7341], [140, 11.3829], [160, 13.6314], [180, 16.0317], [200, 17.2087]]
    },
    {
      "name": "inject/exposed",
      "data": [[0, 3.44935], [20, 3.94023], [40, 3.92209], [60, 4.07821], [80, 5.05153], [100, 6.14977], [120, 5.1516], [140, 5.71287], [160, 6.31992], [180, 6.73667], [200, 7.30428]]
    }
  ]
}
