
{
  "title": {
    "text": "big complexity | clang++ "
  },
  "xAxis": {
    "title": {
      "text": "Number of bindings"
    },
    "floor": 0
  },

  "yAxis": {
    "title": {
      "text": "Time [s]"
    },
    "floor": 0
  },
  "series": [
    {
      "name": "ctor/auto",
      "data": [[0, 7.5097], [20, 7.50191], [40, 7.11243], [60, 4.67641], [80, 5.5925], [100, 5.03977], [120, 5.51038], [140, 5.43576], [160, 6.45235], [180, 5.91461], [200, 6.21363]]
    },
    {
      "name": "inject/all",
      "data": [[0, 3.09493], [20, 3.39489], [40, 4.07342], [60, 4.36838], [80, 3.91343], [100, 4.37336], [120, 4.42918], [140, 4.85473], [160, 5.21578], [180, 5.16013], [200, 5.21173]]
    },
    {
      "name": "ctor/exposed",
      "data": [[0, 4.77301], [20, 4.44462], [40, 5.45319], [60, 6.24399], [80, 7.09177], [100, 7.9967], [120, 8.21976], [140, 10.4333], [160, 10.8581], [180, 13.2518], [200, 12.9745]]
    },
    {
      "name": "inject/exposed",
      "data": [[0, 3.90149], [20, 3.97767], [40, 4.36611], [60, 4.74241], [80, 5.06421], [100, 5.18582], [120, 5.30206], [140, 5.66704], [160, 6.20251], [180, 7.61392], [200, 7.29973]]
    }
  ]
}
