
{
  "title": {
    "text": "big complexity | clang++ "
  },
  "xAxis": {
    "title": {
      "text": "Number of bindings"
    },
    "floor": 0
  },

  "yAxis": {
    "title": {
      "text": "Time [s]"
    },
    "floor": 0
  },
  "series": [
    {
      "name": "ctor/auto",
      "data": [[0, 6.69072], [20, 6.79755], [40, 6.76839], [60, 7.17073], [80, 7.03093], [100, 7.10475], [120, 7.04943], [140, 7.02369], [160, 7.55302], [180, 7.03559], [200, 6.83379]]
    },
    {
      "name": "inject/all",
      "data": [[0, 3.09319], [20, 3.44123], [40, 3.67005], [60, 3.81993], [80, 3.51765], [100, 3.56572], [120, 3.71116], [140, 3.86413], [160, 3.94921], [180, 4.04751], [200, 4.206]]
    },
    {
      "name": "ctor/exposed",
      "data": [[0, 6.0192], [20, 6.9187], [40, 7.39435], [60, 7.68911], [80, 8.25295], [100, 9.1823], [120, 10.8794], [140, 11.7969], [160, 13.2979], [180, 15.0392], [200, 15.7762]]
    },
    {
      "name": "inject/exposed",
      "data": [[0, 3.20599], [20, 3.54712], [40, 3.50342], [60, 10.2016], [80, 4.21695], [100, 4.46094], [120, 4.89393], [140, 5.3629], [160, 6.58027], [180, 6.84048], [200, 6.9931]]
    }
  ]
}
