
{
  "title": {
    "text": "big complexity | g++-5 "
  },
  "xAxis": {
    "title": {
      "text": "Number of bindings"
    },
    "floor": 0
  },

  "yAxis": {
    "title": {
      "text": "Time [s]"
    },
    "floor": 0
  },
  "series": [
    {
      "name": "ctor/auto",
      "data": [[0, 10.1391], [20, 10.1142], [40, 10.5635], [60, 10.7716], [80, 11.1915], [100, 11.3763], [120, 12.0197], [140, 12.355], [160, 14.0616], [180, 13.4897], [200, 13.9636]]
    },
    {
      "name": "inject/all",
      "data": [[0, 8.09825], [20, 8.23947], [40, 8.55194], [60, 10.5075], [80, 9.13211], [100, 9.36894], [120, 9.7311], [140, 10.212], [160, 10.6334], [180, 10.8338], [200, 11.3098]]
    },
    {
      "name": "ctor/exposed",
      "data": [[0, 10.052], [20, 10.8639], [40, 12.6961], [60, 12.6309], [80, 13.6176], [100, 15.7269], [120, 17.735], [140, 20.2039], [160, 23.3755], [180, 25.7416], [200, 27.1742]]
    },
    {
      "name": "inject/exposed",
      "data": [[0, 8.29781], [20, 8.82757], [40, 9.22043], [60, 9.63546], [80, 10.1612], [100, 10.9776], [120, 13.7652], [140, 13.7014], [160, 14.7295], [180, 18.024], [200, 16.1365]]
    }
  ]
}
