
{
  "title": {
    "text": "big complexity | clang++ "
  },
  "xAxis": {
    "title": {
      "text": "Number of bindings"
    },
    "floor": 0
  },

  "yAxis": {
    "title": {
      "text": "Time [s]"
    },
    "floor": 0
  },
  "series": [
    {
      "name": "ctor/auto",
      "data": [[0, 5.90702], [20, 7.84551], [40, 8.69684], [60, 6.30206], [80, 5.92645], [100, 7.44889], [120, 7.50156], [140, 8.34289], [160, 8.79268], [180, 9.3424], [200, 10.5565]]
    },
    {
      "name": "inject/all",
      "data": [[0, 4.98594], [20, 4.72363], [40, 4.74836], [60, 6.26746], [80, 6.4884], [100, 6.21635], [120, 5.55694], [140, 5.48057], [160, 6.46494], [180, 6.83895], [200, 6.40163]]
    },
    {
      "name": "ctor/exposed",
      "data": [[0, 5.22337], [20, 6.01107], [40, 7.29817], [60, 8.85665], [80, 12.891], [100, 15.4878], [120, 18.2416], [140, 18.8046], [160, 26.4494], [180, 20.3622], [200, 14.3284]]
    },
    {
      "name": "inject/exposed",
      "data": [[0, 4.07184], [20, 4.3959], [40, 4.92554], [60, 5.0364], [80, 5.42066], [100, 5.47418], [120, 6.81209], [140, 7.23254], [160, 6.99257], [180, 7.63496], [200, 8.06698]]
    }
  ]
}
