
{
  "title": {
    "text": "big complexity | clang++ "
  },
  "xAxis": {
    "title": {
      "text": "Number of bindings"
    },
    "floor": 0
  },

  "yAxis": {
    "title": {
      "text": "Time [s]"
    },
    "floor": 0
  },
  "series": [
    {
      "name": "ctor/auto",
      "data": [[0, 4.76144], [20, 4.34994], [40, 4.49347], [60, 4.66933], [80, 4.75442], [100, 4.69882], [120, 5.13286], [140, 5.48884], [160, 5.5255], [180, 5.8885], [200, 6.56495]]
    },
    {
      "name": "inject/all",
      "data": [[0, 3.80613], [20, 3.60425], [40, 3.75709], [60, 3.93531], [80, 4.08409], [100, 4.22643], [120, 4.37252], [140, 4.44842], [160, 4.80072], [180, 4.77246], [200, 5.2643]]
    },
    {
      "name": "ctor/exposed",
      "data": [[0, 4.46248], [20, 4.73469], [40, 5.34767], [60, 5.79686], [80, 7.02335], [100, 8.1186], [120, 9.04769], [140, 11.6346], [160, 12.9117], [180, 15.0209], [200, 15.8911]]
    },
    {
      "name": "inject/exposed",
      "data": [[0, 3.64634], [20, 3.57111], [40, 3.92138], [60, 4.44268], [80, 4.69537], [100, 4.97816], [120, 6.01218], [140, 6.35488], [160, 7.40226], [180, 7.9621], [200, 7.73742]]
    }
  ]
}
