
{
  "title": {
    "text": "big complexity | clang++ "
  },
  "xAxis": {
    "title": {
      "text": "Number of bindings"
    },
    "floor": 0
  },

  "yAxis": {
    "title": {
      "text": "Time [s]"
    },
    "floor": 0
  },
  "series": [
    {
      "name": "ctor/auto",
      "data": [[0, 5.09975], [20, 5.06747], [40, 6.09392], [60, 5.59798], [80, 5.69219], [100, 6.25669], [120, 6.0737], [140, 7.14372], [160, 6.59151], [180, 7.09176], [200, 7.5161]]
    },
    {
      "name": "inject/all",
      "data": [[0, 4.03675], [20, 4.24149], [40, 4.15892], [60, 4.26447], [80, 4.61644], [100, 4.91515], [120, 4.82692], [140, 6.52899], [160, 5.27172], [180, 6.74984], [200, 7.57965]]
    },
    {
      "name": "ctor/exposed",
      "data": [[0, 6.33087], [20, 7.18788], [40, 7.6084], [60, 7.89962], [80, 7.70701], [100, 10.1422], [120, 10.4072], [140, 11.3545], [160, 13.1754], [180, 14.8148], [200, 13.7666]]
    },
    {
      "name": "inject/exposed",
      "data": [[0, 3.87883], [20, 4.49046], [40, 5.14864], [60, 4.97455], [80, 5.26583], [100, 5.75485], [120, 6.76772], [140, 7.20017], [160, 8.44162], [180, 8.79825], [200, 9.78021]]
    }
  ]
}
