
{
  "title": {
    "text": "quick complexity | g++-5 "
  },
  "xAxis": {
    "title": {
      "text": "Number of bindings"
    },
    "floor": 0
  },

  "yAxis": {
    "title": {
      "text": "Time [s]"
    },
    "floor": 0
  },
  "series": [
    {
      "name": "ctor/auto",
      "data": [[10, 3.1838]]
    },
    {
      "name": "inject/all",
      "data": [[10, 2.337]]
    },
    {
      "name": "ctor/exposed",
      "data": [[10, 3.43691]]
    },
    {
      "name": "inject/exposed",
      "data": [[10, 2.41811]]
    }
  ]
}
