
{
  "title": {
    "text": "quick complexity | clang++-3.7 "
  },
  "xAxis": {
    "title": {
      "text": "Number of bindings"
    },
    "floor": 0
  },

  "yAxis": {
    "title": {
      "text": "Time [s]"
    },
    "floor": 0
  },
  "series": [
    {
      "name": "ctor/auto",
      "data": [[10, 1.78753]]
    },
    {
      "name": "inject/all",
      "data": [[10, 1.37813]]
    },
    {
      "name": "ctor/exposed",
      "data": [[10, 2.20032]]
    },
    {
      "name": "inject/exposed",
      "data": [[10, 2.16865]]
    }
  ]
}
