
{
  "title": {
    "text": "quick complexity | clang++ "
  },
  "xAxis": {
    "title": {
      "text": "Number of bindings"
    },
    "floor": 0
  },

  "yAxis": {
    "title": {
      "text": "Time [s]"
    },
    "floor": 0
  },
  "series": [
    {
      "name": "ctor/auto",
      "data": [[10, 2.19833]]
    },
    {
      "name": "inject/all",
      "data": [[10, 1.59734]]
    },
    {
      "name": "ctor/exposed",
      "data": [[10, 2.79793]]
    },
    {
      "name": "inject/exposed",
      "data": [[10, 2.13144]]
    }
  ]
}
