
{
  "title": {
    "text": "small complexity | g++-5 "
  },
  "xAxis": {
    "title": {
      "text": "Number of bindings"
    },
    "floor": 0
  },

  "yAxis": {
    "title": {
      "text": "Time [s]"
    },
    "floor": 0
  },
  "series": [
    {
      "name": "ctor/auto",
      "data": [[0, 3.44893], [10, 3.58729], [20, 3.87609], [30, 4.01044], [40, 4.15328], [50, 4.24602], [60, 4.38748], [70, 4.47413], [80, 4.61941], [90, 4.75776], [100, 4.93661]]
    },
    {
      "name": "inject/all",
      "data": [[0, 2.28717], [10, 2.42531], [20, 2.56177], [30, 2.61554], [40, 2.72256], [50, 2.83829], [60, 2.96097], [70, 3.09575], [80, 3.23894], [90, 3.51862], [100, 3.63709]]
    },
    {
      "name": "ctor/exposed",
      "data": [[0, 3.47829], [10, 3.95916], [20, 4.54594], [30, 5.32253], [40, 6.51209], [50, 7.97575], [60, 9.69021], [70, 11.23], [80, 13.3261], [90, 15.3766], [100, 15.7068]]
    },
    {
      "name": "inject/exposed",
      "data": [[0, 2.29675], [10, 2.53307], [20, 2.82824], [30, 3.20812], [40, 3.86136], [50, 4.47287], [60, 5.16336], [70, 6.13455], [80, 7.02824], [90, 7.96159], [100, 8.24315]]
    }
  ]
}
