
{
  "title": {
    "text": "small complexity | clang++ "
  },
  "xAxis": {
    "title": {
      "text": "Number of bindings"
    },
    "floor": 0
  },

  "yAxis": {
    "title": {
      "text": "Time [s]"
    },
    "floor": 0
  },
  "series": [
    {
      "name": "ctor/auto",
      "data": [[0, 2.20469], [10, 3.28361], [20, 1.97809], [30, 1.89322], [40, 2.22382], [50, 2.36625], [60, 2.41453], [70, 2.9192], [80, 3.02914], [90, 2.6536], [100, 2.52027]]
    },
    {
      "name": "inject/all",
      "data": [[0, 1.77761], [10, 1.40335], [20, 1.41808], [30, 1.55472], [40, 1.84586], [50, 1.82534], [60, 3.19797], [70, 2.7323], [80, 2.53208], [90, 1.65176], [100, 1.73024]]
    },
    {
      "name": "ctor/exposed",
      "data": [[0, 2.26752], [10, 4.28389], [20, 4.67889], [30, 3.63774], [40, 6.53612], [50, 6.79809], [60, 8.40725], [70, 8.71198], [80, 8.56438], [90, 11.0318], [100, 10.9182]]
    },
    {
      "name": "inject/exposed",
      "data": [[0, 2.26312], [10, 2.51047], [20, 2.1875], [30, 2.20706], [40, 2.52556], [50, 3.08847], [60, 2.88834], [70, 3.45161], [80, 3.65644], [90, 4.38265], [100, 4.51243]]
    }
  ]
}
