
{
  "title": {
    "text": "small complexity | clang++ "
  },
  "xAxis": {
    "title": {
      "text": "Number of bindings"
    },
    "floor": 0
  },

  "yAxis": {
    "title": {
      "text": "Time [s]"
    },
    "floor": 0
  },
  "series": [
    {
      "name": "ctor/auto",
      "data": [[0, 1.79799], [10, 2.46643], [20, 2.15781], [30, 2.12625], [40, 2.21226], [50, 2.4052], [60, 2.34943], [70, 2.45776], [80, 2.18831], [90, 2.27475], [100, 2.66658]]
    },
    {
      "name": "inject/all",
      "data": [[0, 1.43269], [10, 1.52276], [20, 2.05477], [30, 2.7342], [40, 3.57094], [50, 2.48252], [60, 1.94302], [70, 2.74577], [80, 1.89354], [90, 2.00691], [100, 2.58043]]
    },
    {
      "name": "ctor/exposed",
      "data": [[0, 2.03279], [10, 2.37405], [20, 2.62931], [30, 3.17227], [40, 4.21984], [50, 4.41983], [60, 8.83563], [70, 10.3102], [80, 9.92269], [90, 10.6237], [100, 8.9021]]
    },
    {
      "name": "inject/exposed",
      "data": [[0, 1.62301], [10, 1.65941], [20, 2.00107], [30, 2.17049], [40, 1.9775], [50, 2.73174], [60, 3.446], [70, 4.14294], [80, 5.53835], [90, 6.18273], [100, 5.3144]]
    }
  ]
}
