
{
  "title": {
    "text": "small complexity | g++-6 "
  },
  "xAxis": {
    "title": {
      "text": "Number of bindings"
    },
    "floor": 0
  },

  "yAxis": {
    "title": {
      "text": "Time [s]"
    },
    "floor": 0
  },
  "series": [
    {
      "name": "ctor/auto",
      "data": [[0, 3.11887], [10, 3.14332], [20, 3.26626], [30, 3.37131], [40, 3.49871], [50, 3.62886], [60, 3.72322], [70, 3.96204], [80, 4.00394], [90, 4.08537], [100, 4.23254]]
    },
    {
      "name": "inject/all",
      "data": [[0, 2.58595], [10, 2.35201], [20, 2.98114], [30, 2.48182], [40, 2.59107], [50, 2.69943], [60, 3.87713], [70, 3.62934], [80, 3.14024], [90, 3.32382], [100, 4.71727]]
    },
    {
      "name": "ctor/exposed",
      "data": [[0, 4.488], [10, 3.97311], [20, 4.35731], [30, 5.37569], [40, 5.94394], [50, 7.75035], [60, 8.78498], [70, 10.6417], [80, 13.6254], [90, 15.7747], [100, 17.8627]]
    },
    {
      "name": "inject/exposed",
      "data": [[0, 2.24015], [10, 2.53353], [20, 2.82547], [30, 3.33487], [40, 3.75937], [50, 4.5669], [60, 5.36845], [70, 6.9205], [80, 7.34969], [90, 8.11081], [100, 8.22535]]
    }
  ]
}
