
{
  "title": {
    "text": "small complexity | clang++ "
  },
  "xAxis": {
    "title": {
      "text": "Number of bindings"
    },
    "floor": 0
  },

  "yAxis": {
    "title": {
      "text": "Time [s]"
    },
    "floor": 0
  },
  "series": [
    {
      "name": "ctor/auto",
      "data": [[0, 2.60766], [10, 2.57428], [20, 2.79029], [30, 2.96527], [40, 2.87205], [50, 3.03683], [60, 2.66893], [70, 3.21723], [80, 3.26039], [90, 2.40765], [100, 2.64796]]
    },
    {
      "name": "inject/all",
      "data": [[0, 1.26109], [10, 1.32874], [20, 1.29638], [30, 1.47179], [40, 1.63065], [50, 1.64911], [60, 1.58947], [70, 1.65016], [80, 1.65979], [90, 1.70343], [100, 1.8158]]
    },
    {
      "name": "ctor/exposed",
      "data": [[0, 1.7056], [10, 2.26906], [20, 2.41973], [30, 2.7642], [40, 3.41369], [50, 4.08394], [60, 5.39669], [70, 7.42044], [80, 10.9019], [90, 8.80448], [100, 7.84422]]
    },
    {
      "name": "inject/exposed",
      "data": [[0, 1.45353], [10, 1.58803], [20, 1.71348], [30, 1.74076], [40, 2.44483], [50, 2.26797], [60, 2.98836], [70, 3.98579], [80, 4.67676], [90, 5.3306], [100, 4.48792]]
    }
  ]
}
