
{
  "title": {
    "text": "small complexity | clang++ "
  },
  "xAxis": {
    "title": {
      "text": "Number of bindings"
    },
    "floor": 0
  },

  "yAxis": {
    "title": {
      "text": "Time [s]"
    },
    "floor": 0
  },
  "series": [
    {
      "name": "ctor/auto",
      "data": [[0, 1.93396], [10, 1.77961], [20, 2.09388], [30, 2.0258], [40, 2.33014], [50, 2.13943], [60, 2.21006], [70, 2.05856], [80, 2.10033], [90, 2.20302], [100, 2.21351]]
    },
    {
      "name": "inject/all",
      "data": [[0, 1.37865], [10, 1.3937], [20, 1.38508], [30, 1.38302], [40, 1.47505], [50, 1.56769], [60, 1.58988], [70, 1.73887], [80, 1.79599], [90, 1.99851], [100, 1.99672]]
    },
    {
      "name": "ctor/exposed",
      "data": [[0, 1.92419], [10, 2.07512], [20, 2.53628], [30, 3.10866], [40, 3.60243], [50, 4.49977], [60, 6.19248], [70, 7.21952], [80, 9.76579], [90, 11.1436], [100, 10.1053]]
    },
    {
      "name": "inject/exposed",
      "data": [[0, 1.1866], [10, 1.3122], [20, 1.48294], [30, 1.72403], [40, 2.01209], [50, 2.36102], [60, 2.74784], [70, 3.15471], [80, 3.77401], [90, 4.47931], [100, 4.44406]]
    }
  ]
}
