
{
  "title": {
    "text": "small complexity | g++-5 "
  },
  "xAxis": {
    "title": {
      "text": "Number of bindings"
    },
    "floor": 0
  },

  "yAxis": {
    "title": {
      "text": "Time [s]"
    },
    "floor": 0
  },
  "series": [
    {
      "name": "ctor/auto",
      "data": [[0, 4.38094], [10, 3.54415], [20, 4.40778], [30, 4.45841], [40, 4.39023], [50, 4.45139], [60, 5.86094], [70, 4.33234], [80, 5.32276], [90, 4.70728], [100, 5.59878]]
    },
    {
      "name": "inject/all",
      "data": [[0, 2.60011], [10, 2.95812], [20, 3.34986], [30, 2.62142], [40, 2.95076], [50, 4.249], [60, 4.10695], [70, 3.69745], [80, 4.06629], [90, 3.80881], [100, 5.65623]]
    },
    {
      "name": "ctor/exposed",
      "data": [[0, 4.99844], [10, 4.75741], [20, 5.27048], [30, 7.87028], [40, 7.4425], [50, 10.2325], [60, 11.7203], [70, 12.9971], [80, 17.2829], [90, 18.7619], [100, 21.003]]
    },
    {
      "name": "inject/exposed",
      "data": [[0, 2.42873], [10, 3.3302], [20, 3.45787], [30, 3.83299], [40, 5.12619], [50, 6.58344], [60, 6.48276], [70, 9.00869], [80, 7.94486], [90, 10.0612], [100, 9.89373]]
    }
  ]
}
