
{
  "title": {
    "text": "small complexity | clang++ "
  },
  "xAxis": {
    "title": {
      "text": "Number of bindings"
    },
    "floor": 0
  },

  "yAxis": {
    "title": {
      "text": "Time [s]"
    },
    "floor": 0
  },
  "series": [
    {
      "name": "ctor/auto",
      "data": [[0, 2.17087], [10, 2.54066], [20, 2.84924], [30, 2.96831], [40, 2.90499], [50, 3.4722], [60, 2.46979], [70, 3.11549], [80, 3.29698], [90, 3.12744], [100, 3.03143]]
    },
    {
      "name": "inject/all",
      "data": [[0, 1.50439], [10, 1.35713], [20, 1.41036], [30, 1.45306], [40, 1.77693], [50, 1.54865], [60, 1.80807], [70, 1.75446], [80, 1.81466], [90, 1.62994], [100, 1.96993]]
    },
    {
      "name": "ctor/exposed",
      "data": [[0, 1.65817], [10, 1.89298], [20, 2.36944], [30, 2.65273], [40, 3.1071], [50, 3.71706], [60, 4.85367], [70, 5.81925], [80, 7.16091], [90, 9.39591], [100, 12.0114]]
    },
    {
      "name": "inject/exposed",
      "data": [[0, 1.25354], [10, 1.70909], [20, 1.70421], [30, 1.8243], [40, 2.04959], [50, 2.73388], [60, 2.8439], [70, 3.06729], [80, 4.03345], [90, 4.34248], [100, 4.73452]]
    }
  ]
}
