
{
  "title": {
    "text": "small complexity | clang++ "
  },
  "xAxis": {
    "title": {
      "text": "Number of bindings"
    },
    "floor": 0
  },

  "yAxis": {
    "title": {
      "text": "Time [s]"
    },
    "floor": 0
  },
  "series": [
    {
      "name": "ctor/auto",
      "data": [[0, 5.61227], [10, 5.12615], [20, 4.05495], [30, 5.24341], [40, 6.42025], [50, 6.62136], [60, 4.15346], [70, 2.42144], [80, 2.28766], [90, 2.42117], [100, 2.45635]]
    },
    {
      "name": "inject/all",
      "data": [[0, 1.28455], [10, 1.36838], [20, 1.42997], [30, 1.46136], [40, 1.52728], [50, 1.59175], [60, 1.65056], [70, 1.7766], [80, 1.85547], [90, 2.0631], [100, 1.98369]]
    },
    {
      "name": "ctor/exposed",
      "data": [[0, 1.89441], [10, 2.05753], [20, 2.40589], [30, 2.92264], [40, 3.50675], [50, 4.23509], [60, 5.18156], [70, 6.19861], [80, 7.334], [90, 8.81776], [100, 14.3617]]
    },
    {
      "name": "inject/exposed",
      "data": [[0, 1.89857], [10, 1.78368], [20, 2.62042], [30, 2.48314], [40, 2.88433], [50, 3.74764], [60, 3.49998], [70, 3.43413], [80, 3.9205], [90, 4.35535], [100, 4.39855]]
    }
  ]
}
