
{
  "title": {
    "text": "small complexity | clang++ "
  },
  "xAxis": {
    "title": {
      "text": "Number of bindings"
    },
    "floor": 0
  },

  "yAxis": {
    "title": {
      "text": "Time [s]"
    },
    "floor": 0
  },
  "series": [
    {
      "name": "ctor/auto",
      "data": [[0, 2.05707], [10, 2.24655], [20, 2.2462], [30, 1.9599], [40, 1.9154], [50, 1.95801], [60, 1.99718], [70, 2.02818], [80, 2.09196], [90, 2.18563], [100, 2.3219]]
    },
    {
      "name": "inject/all",
      "data": [[0, 1.37056], [10, 1.30369], [20, 1.36691], [30, 1.36331], [40, 1.51693], [50, 1.53442], [60, 1.61533], [70, 1.55822], [80, 1.65275], [90, 1.71273], [100, 1.80245]]
    },
    {
      "name": "ctor/exposed",
      "data": [[0, 1.76025], [10, 2.09477], [20, 2.58668], [30, 2.83409], [40, 3.50332], [50, 4.66635], [60, 5.90973], [70, 7.39807], [80, 10.2989], [90, 11.2891], [100, 12.1296]]
    },
    {
      "name": "inject/exposed",
      "data": [[0, 1.40397], [10, 1.62475], [20, 1.73037], [30, 1.88182], [40, 2.34525], [50, 2.63329], [60, 3.17967], [70, 3.64347], [80, 4.19181], [90, 5.19194], [100, 5.25057]]
    }
  ]
}
