
{
  "title": {
    "text": "small complexity | clang++ "
  },
  "xAxis": {
    "title": {
      "text": "Number of bindings"
    },
    "floor": 0
  },

  "yAxis": {
    "title": {
      "text": "Time [s]"
    },
    "floor": 0
  },
  "series": [
    {
      "name": "ctor/auto",
      "data": [[0, 2.90324], [10, 3.12429], [20, 2.68072], [30, 3.47894], [40, 3.70116], [50, 2.8798], [60, 2.91304], [70, 2.56514], [80, 2.91072], [90, 4.22312], [100, 4.58232]]
    },
    {
      "name": "inject/all",
      "data": [[0, 2.92303], [10, 2.5379], [20, 2.64975], [30, 2.80736], [40, 2.19129], [50, 2.69526], [60, 2.64537], [70, 2.2119], [80, 2.94728], [90, 3.41395], [100, 2.60611]]
    },
    {
      "name": "ctor/exposed",
      "data": [[0, 2.38559], [10, 2.83321], [20, 4.05773], [30, 2.75175], [40, 3.50221], [50, 4.70541], [60, 5.40272], [70, 6.61584], [80, 7.86762], [90, 10.0605], [100, 10.0042]]
    },
    {
      "name": "inject/exposed",
      "data": [[0, 1.64964], [10, 1.98597], [20, 1.8794], [30, 2.19414], [40, 2.25264], [50, 2.33152], [60, 3.30701], [70, 3.65759], [80, 4.31182], [90, 4.64578], [100, 4.44639]]
    }
  ]
}
