
{
  "title": {
    "text": "small complexity | g++-5 "
  },
  "xAxis": {
    "title": {
      "text": "Number of bindings"
    },
    "floor": 0
  },

  "yAxis": {
    "title": {
      "text": "Time [s]"
    },
    "floor": 0
  },
  "series": [
    {
      "name": "ctor/auto",
      "data": [[0, 2.93535], [10, 2.90724], [20, 3.02843], [30, 3.13375], [40, 3.21916], [50, 3.31632], [60, 3.78555], [70, 3.55316], [80, 3.65777], [90, 3.76001], [100, 3.95285]]
    },
    {
      "name": "inject/all",
      "data": [[0, 2.07091], [10, 2.14126], [20, 2.26242], [30, 2.36767], [40, 2.70793], [50, 2.51046], [60, 2.6458], [70, 2.83279], [80, 2.88198], [90, 2.92366], [100, 3.02964]]
    },
    {
      "name": "ctor/exposed",
      "data": [[0, 3.01939], [10, 3.66042], [20, 4.18301], [30, 4.54541], [40, 5.61614], [50, 6.83904], [60, 8.41084], [70, 9.98485], [80, 11.8284], [90, 14.5302], [100, 16.9617]]
    },
    {
      "name": "inject/exposed",
      "data": [[0, 2.09222], [10, 2.35245], [20, 2.92223], [30, 3.04227], [40, 3.46487], [50, 4.90658], [60, 4.80122], [70, 5.50363], [80, 6.37626], [90, 7.44994], [100, 7.71466]]
    }
  ]
}
