
{
  "title": {
    "text": "small complexity | g++-5 "
  },
  "xAxis": {
    "title": {
      "text": "Number of bindings"
    },
    "floor": 0
  },

  "yAxis": {
    "title": {
      "text": "Time [s]"
    },
    "floor": 0
  },
  "series": [
    {
      "name": "ctor/auto",
      "data": [[0, 3.0184], [10, 3.02972], [20, 3.34833], [30, 3.46217], [40, 3.44198], [50, 4.01452], [60, 3.63691], [70, 3.76454], [80, 3.88255], [90, 4.15472], [100, 4.22281]]
    },
    {
      "name": "inject/all",
      "data": [[0, 2.15581], [10, 2.21293], [20, 2.29736], [30, 2.42368], [40, 2.51322], [50, 2.63764], [60, 2.78534], [70, 2.8986], [80, 3.00017], [90, 3.26982], [100, 3.26163]]
    },
    {
      "name": "ctor/exposed",
      "data": [[0, 3.14849], [10, 3.71645], [20, 4.30156], [30, 5.09514], [40, 6.04413], [50, 7.63425], [60, 8.94224], [70, 11.1252], [80, 12.7783], [90, 16.1127], [100, 18.7738]]
    },
    {
      "name": "inject/exposed",
      "data": [[0, 3.20178], [10, 2.50095], [20, 3.10186], [30, 3.14832], [40, 4.03527], [50, 5.06093], [60, 6.61859], [70, 6.59326], [80, 6.85379], [90, 8.15486], [100, 8.94281]]
    }
  ]
}
