
{
  "title": {
    "text": "small complexity | g++-5 "
  },
  "xAxis": {
    "title": {
      "text": "Number of bindings"
    },
    "floor": 0
  },

  "yAxis": {
    "title": {
      "text": "Time [s]"
    },
    "floor": 0
  },
  "series": [
    {
      "name": "ctor/auto",
      "data": [[0, 3.1101], [10, 2.95623], [20, 3.18128], [30, 3.10218], [40, 3.21281], [50, 3.36852], [60, 3.43558], [70, 3.62024], [80, 3.67061], [90, 3.76292], [100, 3.97476]]
    },
    {
      "name": "inject/all",
      "data": [[0, 2.13142], [10, 2.25135], [20, 2.23528], [30, 2.33335], [40, 2.40439], [50, 2.49468], [60, 2.60085], [70, 2.80972], [80, 2.8207], [90, 3.06772], [100, 3.0583]]
    },
    {
      "name": "ctor/exposed",
      "data": [[0, 2.93484], [10, 3.29053], [20, 3.79155], [30, 4.53989], [40, 5.6575], [50, 6.58946], [60, 8.63897], [70, 9.74168], [80, 11.5569], [90, 13.7931], [100, 14.1359]]
    },
    {
      "name": "inject/exposed",
      "data": [[0, 2.08765], [10, 2.30262], [20, 2.56991], [30, 2.91889], [40, 3.41372], [50, 4.01749], [60, 4.71521], [70, 5.42638], [80, 6.11241], [90, 7.12148], [100, 7.41139]]
    }
  ]
}
